d3sdk/__init__.py
d3sdk/d3_dataframe_db.py
d3sdk/k2box_dataframe_db.py
d3sdk/pgrepo_dataframe_db.py
d3sdk/model/__init__.py
d3sdk/model/alarm_group_detail.py
d3sdk/model/business_model_define.py
d3sdk/model/device_failure_record.py
d3sdk/util/__init__.py
d3sdk/util/business_util.py
d3sdk-0.1.29.dist-info/METADATA
d3sdk-0.1.29.dist-info/WHEEL
d3sdk-0.1.29.dist-info/top_level.txt
d3sdk-0.1.29.dist-info/RECORD
