Metadata-Version: 2.1
Name: d3sdk
Version: 0.1.29
Summary: 3DS平台业务层的数据查询SDK
Home-page: UNKNOWN
Author: K2data
Author-email: admin@k2data.com.cn
License: UNKNOWN
Platform: UNKNOWN
Classifier: Development Status :: 3 - Alpha
Classifier: Intended Audience :: Developers
Classifier: Programming Language :: Python :: 3
Classifier: Programming Language :: Python :: 3.7
Classifier: Programming Language :: Python :: 3.8
Classifier: Programming Language :: Python :: 3.9
Classifier: Programming Language :: Python :: 3.10
Classifier: Operating System :: OS Independent
Classifier: Topic :: Software Development :: Libraries
Requires-Python: >=3.7
Requires-Dist: k2magic
Requires-Dist: psycopg2-binary==2.8.6
